pyshellman/__init__.py
pyshellman/exception.py
pyshellman/output.py
pyshellman/pip.py
pyshellman/protocol.py
pyshellman/python.py
pyshellman/shell.py
pyshellman-0.2.0.dist-info/METADATA
pyshellman-0.2.0.dist-info/WHEEL
pyshellman-0.2.0.dist-info/top_level.txt
pyshellman-0.2.0.dist-info/RECORD
