Metadata-Version: 2.4
Name: PyShellMan
Version: 0.2.0
Requires-Python: >=3.10
Requires-Dist: rich<14,>=13.5
Requires-Dist: MDit<0.2,>=0.1
Requires-Dist: ExceptionMan<0.2,>=0.1
Requires-Dist: ANSI-SGR<0.2,>=0.1
